france_travail_api/__init__.py
france_travail_api/_url.py
france_travail_api/client.py
france_travail_api/exceptions.py
france_travail_api/auth/__init__.py
france_travail_api/auth/_credentials.py
france_travail_api/auth/_token.py
france_travail_api/auth/scope.py
france_travail_api/http_transport/__init__.py
france_travail_api/http_transport/_http_client.py
france_travail_api/http_transport/_http_response.py
france_travail_api/offres/__init__.py
france_travail_api/offres/_client.py
france_travail_api/offres/_referentiels_client.py
france_travail_api/offres/models/__init__.py
france_travail_api/offres/models/agence.py
france_travail_api/offres/models/competence.py
france_travail_api/offres/models/contact.py
france_travail_api/offres/models/contexte_travail.py
france_travail_api/offres/models/contrat.py
france_travail_api/offres/models/entreprise.py
france_travail_api/offres/models/exigence.py
france_travail_api/offres/models/experience.py
france_travail_api/offres/models/formation.py
france_travail_api/offres/models/langue.py
france_travail_api/offres/models/lieu_travail.py
france_travail_api/offres/models/metier.py
france_travail_api/offres/models/offre.py
france_travail_api/offres/models/origine_offre.py
france_travail_api/offres/models/permis.py
france_travail_api/offres/models/qualite_pro.py
france_travail_api/offres/models/salaire.py
france_travail_api/offres/models/search_params.py
france_travail_api-1.5.0.dist-info/METADATA
france_travail_api-1.5.0.dist-info/WHEEL
france_travail_api-1.5.0.dist-info/licenses/LICENSE
france_travail_api-1.5.0.dist-info/RECORD
