Metadata-Version: 2.4
Name: france-travail-api
Version: 1.5.0
Summary: A Python SDK for France Travail API
Project-URL: Bug Tracker, https://github.com/cmnemoi/france_travail_api/issues
Project-URL: Changelog, https://github.com/cmnemoi/france_travail_api/blob/main/CHANGELOG.md
Project-URL: Homepage, https://github.com/cmnemoi/france_travail_api/
Project-URL: Repository, https://github.com/cmnemoi/france_travail_api/
Author-email: Charles-Meldhine Madi Mnemoi <charlesmeldhine.madimnemoi@gmail.com>
License-Expression: Apache-2.0
License-File: LICENSE
Classifier: Development Status :: 3 - Alpha
Classifier: Operating System :: OS Independent
Classifier: Programming Language :: Python :: 3
Classifier: Programming Language :: Python :: 3.10
Classifier: Programming Language :: Python :: 3.11
Classifier: Programming Language :: Python :: 3.12
Classifier: Programming Language :: Python :: 3.13
Classifier: Programming Language :: Python :: 3.14
Requires-Python: <3.15,>=3.10
Requires-Dist: httpx>=0.28.1
